.mica_settings
.project
.pydevproject
MANIFEST.in
ez_setup.py
setup.cfg
setup.py
.settings/org.eclipse.ltk.core.refactoring.prefs
hildon/maegen.desktop
hildon/icons/48x48/maegen.png
hildon/icons/64x64/maegen.png
media/images/maegen-logo.jpg
scripts/maegen
src/maegen/__init__.py
src/maegen/bootstrap.py
src/maegen/female.png
src/maegen/maegen-logo.jpg
src/maegen/male.png
src/maegen.egg-info/PKG-INFO
src/maegen.egg-info/SOURCES.txt
src/maegen.egg-info/dependency_links.txt
src/maegen.egg-info/not-zip-safe
src/maegen.egg-info/requires.txt
src/maegen.egg-info/top_level.txt
src/maegen/common/__init__.py
src/maegen/common/version.py
src/maegen/core/__init__.py
src/maegen/core/exceptions.py
src/maegen/core/gedcom.py
src/maegen/core/maegen.py
src/maegen/gui/__init__.py
src/maegen/gui/gtk/__init__.py
src/maegen/gui/gtk/utils.py
src/maegen/gui/gtk/widget.py
src/maegen/gui/hildon/__init__.py
src/maegen/gui/hildon/maegenGui.py
src/maegen/gui/hildon/mock.py
src/maegen/gui/hildon/utils.py