Metadata-Version: 1.0
Name: maegen
Version: 0.2.0
Summary: Maegen is a genealogical application for N900
Home-page: http://blog.maegen.bressure.net
Author: Thierry Bressure
Author-email: maegen@bressure.net
License: UNKNOWN
Download-URL: http://maegen.bressure.net
Platform: UNKNOWN
Classifier: Development Status :: 2 - Pre-Alpha
Classifier: Environment :: Handhelds/PDA's
Classifier: Intended Audience :: End Users/Desktop
Classifier: Intended Audience :: Developers
Classifier: License :: OSI Approved :: GNU Library or Lesser General Public License (LGPL)
Classifier: Operating System :: POSIX :: Linux
Classifier: Programming Language :: Python
